limbo/__init__.py
limbo/_limbo.pyi
limbo/_limbo.pypy310-pp73-x86_64-linux-gnu.so
limbo/py.typed
pylimbo-0.0.22.dist-info/METADATA
pylimbo-0.0.22.dist-info/WHEEL
pylimbo-0.0.22.dist-info/RECORD
