Metadata-Version: 2.4
Name: pylimbo
Version: 0.0.22
Classifier: Development Status :: 3 - Alpha
Classifier: Programming Language :: Python
Classifier: Programming Language :: Python :: 3
Classifier: Programming Language :: Python :: 3 :: Only
Classifier: Programming Language :: Python :: 3.9
Classifier: Programming Language :: Python :: 3.10
Classifier: Programming Language :: Python :: 3.11
Classifier: Programming Language :: Python :: 3.12
Classifier: Programming Language :: Python :: 3.13
Classifier: Programming Language :: Rust
Classifier: License :: OSI Approved :: MIT License
Classifier: Operating System :: POSIX :: Linux
Classifier: Operating System :: Microsoft :: Windows
Classifier: Operating System :: MacOS
Classifier: Topic :: Database
Classifier: Topic :: Software Development :: Libraries
Classifier: Topic :: Software Development :: Libraries :: Python Modules
Classifier: Topic :: Database :: Database Engines/Servers
Requires-Dist: typing-extensions>=4.6.0,!=4.7.0
Requires-Dist: mypy==1.11.0 ; extra == 'dev'
Requires-Dist: pytest==8.3.1 ; extra == 'dev'
Requires-Dist: pytest-cov==5.0.0 ; extra == 'dev'
Requires-Dist: ruff==0.5.4 ; extra == 'dev'
Requires-Dist: coverage==7.6.1 ; extra == 'dev'
Requires-Dist: maturin==1.7.8 ; extra == 'dev'
Provides-Extra: dev
Summary: Limbo is a work-in-progress, in-process OLTP database management system, compatible with SQLite.
Author: the Limbo authors
License: MIT
Requires-Python: >=3.9
Project-URL: Homepage, https://github.com/tursodatabase/limbo
Project-URL: Source, https://github.com/tursodatabase/limbo
